LICENSE
MANIFEST.in
setup.py
Cape.egg-info/PKG-INFO
Cape.egg-info/SOURCES.txt
Cape.egg-info/dependency_links.txt
Cape.egg-info/entry_points.txt
Cape.egg-info/pbr.json
Cape.egg-info/top_level.txt
cape/__init__.py
cape/__main__.py