Metadata-Version: 1.1
Name: Cape
Version: 2.0.0
Summary: An implementation of Cape in Python.
Home-page: https://github.com/colinta/Cape.py
Author: Giovanni Blu Mitolo <gioscarab@gmail.com>, Colin T.A. Gray <colinta@gmail.com>
Author-email: gioscarab@gmail.com
License: BSD
Keywords: crypt
Platform: any
Classifier: Programming Language :: Python
Classifier: Development Status :: 4 - Beta
Classifier: Environment :: Console
Classifier: License :: OSI Approved :: Apache Software License
Classifier: Operating System :: OS Independent
Classifier: Intended Audience :: End Users/Desktop
Classifier: Intended Audience :: Developers
Classifier: Intended Audience :: System Administrators
Classifier: Topic :: Security :: Cryptography
